pyrotein/__init__.py
pyrotein/angle.py
pyrotein/atom.py
pyrotein/distance.py
pyrotein/fasta.py
pyrotein/misc.py
pyrotein/search_rcsb.py
pyrotein/utils.py
pyrotein-0.1.4.dist-info/LICENSE
pyrotein-0.1.4.dist-info/METADATA
pyrotein-0.1.4.dist-info/WHEEL
pyrotein-0.1.4.dist-info/top_level.txt
pyrotein-0.1.4.dist-info/RECORD
