Metadata-Version: 2.1
Name: pyrotein
Version: 0.1.4
Summary: A tiny package for structure analysis of macromolecules.
Home-page: https://github.com/carbonscott/pyrotein
Author: Cong Wang
Author-email: wangimagine@gmail.com
License: UNKNOWN
Keywords: PDB,structure biology,protein,analysis
Platform: UNKNOWN
Classifier: Programming Language :: Python :: 3
Classifier: License :: OSI Approved :: MIT License
Classifier: Operating System :: OS Independent
Requires-Python: >=3.6
